MANIFEST.in
README.txt
setup.py
conny_utils.egg-info/PKG-INFO
conny_utils.egg-info/SOURCES.txt
conny_utils.egg-info/dependency_links.txt
conny_utils.egg-info/requires.txt
conny_utils.egg-info/top_level.txt
myPackage/Common.py
myPackage/IOUtil.py
myPackage/__init__.py
myPackage/hellomodule.py
myPackage/somePython.py
myPackage/packageData/sampleData.dat