Metadata-Version: 1.0
Name: conny-utils
Version: 0.2
Summary: Some usefull functions for machine learning
Home-page: UNKNOWN
Author: CPflaume
Author-email: constantin.pflaume@gmail.com
License: MIT
Platform: UNKNOWN
